<?xml version="1.0" encoding="utf-8"?>
<Resources Culture="en-US">
	<Group Type="String">
		<Items>
			<Item Name="Caption" Value="Клієнти (FreedomUI)" />
			<Item Name="Columns.UsrClientsCode.Caption" Value="Код" />
			<Item Name="Columns.UsrClientsManager.Caption" Value="Відповідальний менеджер" />
			<Item Name="Columns.UsrClientsPhone.Caption" Value="Телефон" />
			<Item Name="Columns.UsrClientsType.Caption" Value="Тип" />
			<Item Name="Columns.UsrName.Caption" Value="ПІБ" />
		</Items>
	</Group>
</Resources>